hivclustering/__init__.py
hivclustering/mtnetwork.py
hivclustering/networkbuild.py
hivclustering/data/HBL/CycleSupport.bf
hivclustering/data/HBL/DegreeDistributions.bf
hivclustering/data/HBL/ExtractACluster.bf
hivclustering/data/HBL/ExtractSequences.bf
hivclustering/data/HBL/SimulateSequence.bf
hivclustering/data/HBL/TriangleSupport.bf
hivclustering-1.9.6.data/scripts/TNS
hivclustering-1.9.6.data/scripts/hivnetworkannotate
hivclustering-1.9.6.data/scripts/hivnetworkcsv
hivclustering-1.9.6.dist-info/METADATA
hivclustering-1.9.6.dist-info/WHEEL
hivclustering-1.9.6.dist-info/top_level.txt
hivclustering-1.9.6.dist-info/RECORD
