Metadata-Version: 2.4
Name: hivclustering
Version: 1.9.6
Summary: HIV molecular clustering tools
Home-page: http://github.com/veg/hivclustering
Author: Sergei Kosakovsky Pond
Author-email: spond@ucsd.edu
License: MIT License
Requires-Python: >=3.10
Provides-Extra: edgefiltering
Requires-Dist: bioext>=0.21.0; extra == "edgefiltering"
Requires-Dist: hyphy-python>=0.1.11; extra == "edgefiltering"
Requires-Dist: hppy>=0.9.9; extra == "edgefiltering"
Dynamic: author
Dynamic: author-email
Dynamic: home-page
Dynamic: license
Dynamic: provides-extra
Dynamic: requires-python
Dynamic: summary
